teas/__init__.py
teas/data_products.py
teas/helpers.py
teas/spectra.py
teas-0.1.1.dist-info/LICENSE
teas-0.1.1.dist-info/METADATA
teas-0.1.1.dist-info/WHEEL
teas-0.1.1.dist-info/top_level.txt
teas-0.1.1.dist-info/RECORD
