Metadata-Version: 2.1
Name: teas
Version: 0.1.1
Summary: Tools for the Extraction and Analysis of Spectra from JWST observations
Home-page: https://github.com/joelenehales/teas
Author: Joelene Hales
Author-email: <joelenehales@bell.net>
Keywords: python,astronomy,jwst,spectroscopy
Classifier: Development Status :: 4 - Beta
Classifier: License :: OSI Approved :: MIT License
Classifier: Intended Audience :: Science/Research
Classifier: Topic :: Scientific/Engineering :: Astronomy
Classifier: Programming Language :: Python :: 3
Classifier: Operating System :: OS Independent
License-File: LICENSE
Requires-Dist: jdaviz ==3.1
Requires-Dist: reproject >=0.9.1
Requires-Dist: chardet
Requires-Dist: asdf ==2.13.0
